PythonTool/__init__.py
PythonTool/main.py
PythonTool-0.4.0.2.dist-info/METADATA
PythonTool-0.4.0.2.dist-info/WHEEL
PythonTool-0.4.0.2.dist-info/top_level.txt
PythonTool-0.4.0.2.dist-info/RECORD
