Metadata-Version: 2.1
Name: PythonTool
Version: 0.4.0.2
Summary: A package for tools in Python
Author: Zhu Chongjing
Author-email: tommy1008@dingtalk.com
Classifier: Programming Language :: Python :: 3
Classifier: License :: OSI Approved :: MIT License
Classifier: Operating System :: OS Independent
Requires-Dist: manim
